pre_commit_nb/__init__.py
pre_commit_nb/base64_to_external_storage.py
pre_commit_nb/base64_to_image_files.py
pre_commit_nb/common.py
pre_commit_nb-0.2.2a1.dist-info/LICENSE
pre_commit_nb-0.2.2a1.dist-info/METADATA
pre_commit_nb-0.2.2a1.dist-info/WHEEL
pre_commit_nb-0.2.2a1.dist-info/entry_points.txt
pre_commit_nb-0.2.2a1.dist-info/top_level.txt
pre_commit_nb-0.2.2a1.dist-info/RECORD
