Metadata-Version: 2.1
Name: pre-commit-nb
Version: 0.2.2a1
Summary: Set of git pre-commit hooks for Jupyter Notebooks compatible with https://pre-commit.com/ framework
Home-page: http://github.com/karolzak/pre-commit-nb
Author: Karol Zak
Author-email: karol.zak@hotmail.com
License: MIT
Platform: UNKNOWN
Classifier: Development Status :: 5 - Production/Stable
Classifier: Intended Audience :: Developers
Classifier: Intended Audience :: Education
Classifier: Intended Audience :: Science/Research
Classifier: License :: OSI Approved :: MIT License
Classifier: Programming Language :: Python :: 3.5
Classifier: Programming Language :: Python :: 3.6
Classifier: Programming Language :: Python :: 3.7
Classifier: Programming Language :: Python :: 3.8
Classifier: Topic :: Software Development :: Libraries
Classifier: Topic :: Software Development :: Libraries :: Python Modules
